README.md
setup.py
ML_APIs/__init__.py
ML_APIs/google.py
ML_APIs/utils.py
ML_APIs.egg-info/PKG-INFO
ML_APIs.egg-info/SOURCES.txt
ML_APIs.egg-info/dependency_links.txt
ML_APIs.egg-info/requires.txt
ML_APIs.egg-info/top_level.txt
ML_APIs/cloud/__init__.py
ML_APIs/cloud/nlp_cloud.py
ML_APIs/cloud/video_cloud.py
ML_APIs/cloud/vision_cloud.py
ML_APIs/local/__init__.py
ML_APIs/local/nlp_local.py
ML_APIs/local/video_local.py
ML_APIs/local/vision_local.py