Metadata-Version: 2.1
Name: ML-APIs
Version: 0.0.3
Summary: A package for google ML_APIs.
Home-page: https://santhoshse7en.github.io/ML_APIs
Author: M Santhosh Kumar
Author-email: santhoshse7en@gmail.com
License: UNKNOWN
Platform: UNKNOWN
Classifier: Development Status :: 4 - Beta
Classifier: Intended Audience :: End Users/Desktop
Classifier: Intended Audience :: Developers
Classifier: Intended Audience :: System Administrators
Classifier: License :: OSI Approved :: GNU General Public License v3 (GPLv3)
Classifier: Operating System :: OS Independent
Classifier: Programming Language :: Python
Classifier: Topic :: Communications :: Email
Classifier: Topic :: Office/Business
Classifier: Topic :: Software Development :: Bug Tracking
